asyncache/__init__.py
asyncache-0.3.0.dist-info/LICENSE
asyncache-0.3.0.dist-info/WHEEL
asyncache-0.3.0.dist-info/METADATA
asyncache-0.3.0.dist-info/RECORD
