Metadata-Version: 2.1
Name: asyncache
Version: 0.3.0
Summary: Helpers to use cachetools with async code.
License: MIT
Author: hephex
Author-email: figus.federico@gmail.com
Requires-Python: >=3.8,<4.0
Classifier: License :: OSI Approved :: MIT License
Classifier: Programming Language :: Python :: 3
Classifier: Programming Language :: Python :: 3.8
Classifier: Programming Language :: Python :: 3.9
Classifier: Programming Language :: Python :: 3.10
Requires-Dist: cachetools (>=5.2.0,<6.0.0)
Requires-Dist: mypy (>=0.982,<0.983)
Requires-Dist: types-cachetools (>=5.2.1,<6.0.0)
